{
    "key": "group_5b4e51358605d",
    "title": "2 Column w\/ Heading",
    "fields": [
        {
            "key": "field_5b4e52267c973",
            "label": "Title",
            "name": "two_col_heading_title",
            "type": "textarea",
            "instructions": "",
            "required": 0,
            "conditional_logic": 0,
            "wrapper": {
                "width": "",
                "class": "",
                "id": ""
            },
            "default_value": "",
            "placeholder": "",
            "maxlength": "",
            "rows": 3,
            "new_lines": "br"
        },
        {
            "key": "field_5b4e51358b431",
            "label": "Left Content",
            "name": "two_col_heading_l_content",
            "type": "wysiwyg",
            "instructions": "",
            "required": 0,
            "conditional_logic": 0,
            "wrapper": {
                "width": "",
                "class": "",
                "id": ""
            },
            "default_value": "",
            "tabs": "all",
            "toolbar": "full",
            "media_upload": 1,
            "delay": 0
        },
        {
            "key": "field_5b4e521a7c972",
            "label": "Right Content",
            "name": "two_col_heading_r_content",
            "type": "wysiwyg",
            "instructions": "",
            "required": 0,
            "conditional_logic": 0,
            "wrapper": {
                "width": "",
                "class": "",
                "id": ""
            },
            "default_value": "",
            "tabs": "all",
            "toolbar": "full",
            "media_upload": 1,
            "delay": 0
        }
    ],
    "location": [
        [
            {
                "param": "post_template",
                "operator": "==",
                "value": "default"
            }
        ],
        [
            {
                "param": "post_type",
                "operator": "==",
                "value": "location"
            }
        ],
        [
            {
                "param": "post_template",
                "operator": "==",
                "value": "templates\/template-home.php"
            }
        ]
    ],
    "menu_order": 0,
    "position": "normal",
    "style": "default",
    "label_placement": "top",
    "instruction_placement": "label",
    "hide_on_screen": "",
    "active": 0,
    "description": "Two columns with text blocks and a headline above them aligned to the top of their boxes. A toggle switches the side of the image and the content",
    "modified": 1532446928
}